LICENSE
dsmigrator/__init__.py
dsmigrator/__main__.py
dsmigrator/agents.py
dsmigrator/api.py
dsmigrator/computer_groups.py
dsmigrator/iplists.py
dsmigrator/lists.py
dsmigrator/logging.py
dsmigrator/migrator_utils.py
dsmigrator/policies.py
dsmigrator/proxies.py
dsmigrator/proxy.py
dsmigrator/rules_migrator.py
dsmigrator/syslogs.py
dsmigrator/tasks.py
dsmigrator/workload_security_link.py
dsmigrator-1.0.0.dist-info/entry_points.txt
dsmigrator-1.0.0.dist-info/LICENSE
dsmigrator-1.0.0.dist-info/WHEEL
dsmigrator-1.0.0.dist-info/METADATA
dsmigrator-1.0.0.dist-info/RECORD
