Metadata-Version: 2.1
Name: dsmigrator
Version: 1.0.0
Summary: A cli tool to migrate Trend Micro Deep Security to the cloud.
Home-page: https://github.com/ajaxbits/ds-migrator
License: GPLv3
Keywords: Trend,Micro,deepsecurity,cloudone,migrator,trendmicro,security,cli
Author: Alex Jackson
Author-email: alex_jackson@trendmicro.com
Requires-Python: >=3.7,<4.0
Classifier: License :: Other/Proprietary License
Classifier: Programming Language :: Python :: 3
Classifier: Programming Language :: Python :: 3.7
Classifier: Programming Language :: Python :: 3.8
Classifier: Programming Language :: Python :: 3.9
Requires-Dist: PyYAML (>=5.4.1,<6.0.0)
Requires-Dist: click (>=7.1.2,<8.0.0)
Requires-Dist: deep-security-api (>=20.0.463,<21.0.0)
Requires-Dist: python-dateutil (>=2.8.1,<3.0.0)
Requires-Dist: requests (>=2.25.1,<3.0.0)
Requires-Dist: rich (>=10.9.0,<11.0.0)
Requires-Dist: urllib3 (>=1.26.5,<2.0.0)
